Workbook

Sheet Competition Rules & Strategy
A1: BLOOMBERG GLOBAL TRADING CHALLENGE — DALLAS COLLEGE
A2: Strategy Playbook & Mathematical Risk Framework | Synced: 2026-10-06 16:23:25
A4: 1. OFFICIAL COMPETITION RULES & CONSTRAINTS
A5: Rule Name | B5: Constraint | C5: Strategic Playbook Directive
A6: Asset Class | B6: Long-Only Equities | C6: Strictly no options, no shorting, no leverage.
A7: Benchmark Universe | B7: World Large/Mid Cap Index (WLS Index) | C7: Must be index constituents; no penny stocks.
A8: Position Sizing Limit | B8: Maximum 20% of Portfolio Value at Entry | C8: Limits catastrophic drawdown from single earnings miss.
A9: Minimum Security Price | B9: > $5.00 per share | C9: Guarantees liquidity and realistic fill simulation.
A10: Capital Recycling | B10: Active Rebalancing Allowed | C10: Take profits on catalyst peaks and redeploy into next 20% clip.
A12: 2. MATHEMATICAL REALITY: STOCK PREDICTION VS. RISK/REWARD RATIO
A13: Strategy Scenario | B13: Win Rate | C13: Wins (of 10) | D13: Avg Win ($) | E13: Losses (of 10) | F13: Avg Loss ($) | G13: Total Wins ($) | H13: Total Losses ($) | I13: Net Profit/Loss ($)
A14: Scenario A: High Prediction, Poor Risk | B14: 0.8 | C14: 8 | D14: 100 | E14: 2 | F14: 600 | G14: =C14*D14 | H14: =E14*F14 | I14: =G14-H14
A15: Scenario B: Low Prediction, Asymmetric 3:1 R/R | B15: 0.4 | C15: 4 | D15: 300 | E15: 6 | F15: 100 | G15: =C15*D15 | H15: =E15*F15 | I15: =G15-H15

Sheet Remote Live Screener
A1: LIVE CANDIDATE SCREENER — REMOTE ACCESSIBLE
A2: Terminal data baked as values; dynamic Excel formulas compute Target Upside, Stop Losses, and Asymmetric Risk/Reward.
A4: SYMBOL | B4: NAME | C4: SECTOR | D4: LAST PRICE | E4: 1D CHG % | F4: 5D CHG % | G4: WALL ST TARGET | H4: TARGET UPSIDE % | I4: 7% STOP LOSS | J4: $ RISK/SH | K4: $ REWARD/SH | L4: RISK/REWARD RATIO | M4: SIGNAL | N4: BUY RECS | O4: HOLD RECS | P4: SELL RECS | Q4: BUY % | R4: ROE % | S4: P/E RATIO | T4: MARKET CAP | U4: VOLUME | V4: EARNINGS DATE
A5: AVGO | B5: BROADCOM INC | C5: Information Technology | D5: 375.81 | E5: 0.03668864 | F5: 0.0583216 | G5: 529.70209 | H5: =(G5-D5)/D5 | I5: =D5*0.93 | J5: =D5-I5 | K5: =G5-D5 | L5: =IF(J5>0, K5/J5, 0) | M5: =IF(L5>=3.0, "STRONG BUY (3:1+)", IF(L5>=2.0, "QUALIFIED (2:1+)", "MONITOR")) | N5: 58 | O5: 4 | P5: 0 | Q5: =IF((N5+O5+P5)>0, N5/(N5+O5+P5), 0) | R5: 44.245434 | S5: 45.080172 | T5: 1.7939778e+12 | U5: 30717692 | V5: 2026-12-11
A6: NVDA | B6: NVIDIA CORP | C6: Information Technology | D6: 239.24 | E6: 0.00142319 | F6: 0.05294661 | G6: 323.88876 | H6: =(G6-D6)/D6 | I6: =D6*0.93 | J6: =D6-I6 | K6: =G6-D6 | L6: =IF(J6>0, K6/J6, 0) | M6: =IF(L6>=3.0, "STRONG BUY (3:1+)", IF(L6>=2.0, "QUALIFIED (2:1+)", "MONITOR")) | N6: 79 | O6: 2 | P6: 1 | Q6: =IF((N6+O6+P6)>0, N6/(N6+O6+P6), 0) | R6: 117.2107 | S6: 34.401896 | T6: 5765684000000 | U6: 100692456 | V6: 2026-11-19
A7: AMZN | B7: AMAZON.COM INC | C7: Consumer Discretionary | D7: 256.29 | E7: 0.01945107 | F7: 0.03899947 | G7: 332.63547 | H7: =(G7-D7)/D7 | I7: =D7*0.93 | J7: =D7-I7 | K7: =G7-D7 | L7: =IF(J7>0, K7/J7, 0) | M7: =IF(L7>=3.0, "STRONG BUY (3:1+)", IF(L7>=2.0, "QUALIFIED (2:1+)", "MONITOR")) | N7: 77 | O7: 4 | P7: 0 | Q7: =IF((N7+O7+P7)>0, N7/(N7+O7+P7), 0) | R7: 30.558338 | S7: 35.605448 | T7: 2.7644243e+12 | U7: 32765498 | V7: 2026-10-30
A8: UNH | B8: UNITEDHEALTH GROUP INC | C8: Health Care | D8: 376.32 | E8: -0.005969676 | F8: 0.003680589 | G8: 481.11111 | H8: =(G8-D8)/D8 | I8: =D8*0.93 | J8: =D8-I8 | K8: =G8-D8 | L8: =IF(J8>0, K8/J8, 0) | M8: =IF(L8>=3.0, "STRONG BUY (3:1+)", IF(L8>=2.0, "QUALIFIED (2:1+)", "MONITOR")) | N8: 25 | O8: 5 | P8: 0 | Q8: =IF((N8+O8+P8)>0, N8/(N8+O8+P8), 0) | R8: 14.621242 | S8: 21.131109 | T8: 3.3778289e+11 | U8: 4800153 | V8: 2026-10-13
A9: GE | B9: GENERAL ELECTRIC | C9: Industrials | D9: 309.39 | E9: 0.009956258 | F9: -0.02673881 | G9: 393 | H9: =(G9-D9)/D9 | I9: =D9*0.93 | J9: =D9-I9 | K9: =G9-D9 | L9: =IF(J9>0, K9/J9, 0) | M9: =IF(L9>=3.0, "STRONG BUY (3:1+)", IF(L9>=2.0, "QUALIFIED (2:1+)", "MONITOR")) | N9: 21 | O9: 3 | P9: 2 | Q9: =IF((N9+O9+P9)>0, N9/(N9+O9+P9), 0) | R9: 48.794018 | S9: 42.843898 | T9: 3.2101147e+11 | U9: 3426796 | V9: 2026-10-20
A10: RTX | B10: RTX CORP | C10: Industrials | D10: 183.29 | E10: -0.005642055 | F10: -0.01952498 | G10: 230.56522 | H10: =(G10-D10)/D10 | I10: =D10*0.93 | J10: =D10-I10 | K10: =G10-D10 | L10: =IF(J10>0, K10/J10, 0) | M10: =IF(L10>=3.0, "STRONG BUY (3:1+)", IF(L10>=2.0, "QUALIFIED (2:1+)", "MONITOR")) | N10: 19 | O10: 7 | P10: 1 | Q10: =IF((N10+O10+P10)>0, N10/(N10+O10+P10), 0) | R10: 12.017861 | S10: 26.490917 | T10: 2.4703059e+11 | U10: 4168604 | V10: 2026-10-20
A11: GS | B11: GOLDMAN SACHS GROUP INC | C11: Financials | D11: 897.18 | E11: 0.004163589 | F11: -0.02080241 | G11: 1123.7727 | H11: =(G11-D11)/D11 | I11: =D11*0.93 | J11: =D11-I11 | K11: =G11-D11 | L11: =IF(J11>0, K11/J11, 0) | M11: =IF(L11>=3.0, "STRONG BUY (3:1+)", IF(L11>=2.0, "QUALIFIED (2:1+)", "MONITOR")) | N11: 11 | O11: 16 | P11: 1 | Q11: =IF((N11+O11+P11)>0, N11/(N11+O11+P11), 0) | R11: 18.335567 | S11: 13.72168 | T11: 2.7159731e+11 | U11: 2046129 | V11: 2026-10-13
A12: LMT | B12: LOCKHEED MARTIN CORP | C12: Industrials | D12: 510.12 | E12: 0.006888656 | F12: -0.004080358 | G12: 638.82611 | H12: =(G12-D12)/D12 | I12: =D12*0.93 | J12: =D12-I12 | K12: =G12-D12 | L12: =IF(J12>0, K12/J12, 0) | M12: =IF(L12>=3.0, "STRONG BUY (3:1+)", IF(L12>=2.0, "QUALIFIED (2:1+)", "MONITOR")) | N12: 13 | O12: 13 | P12: 1 | Q12: =IF((N12+O12+P12)>0, N12/(N12+O12+P12), 0) | R12: 89.164657 | S12: 23.546662 | T12: 1.1773098e+11 | U12: 849370 | V12: 2026-10-22
A13: GOOGL | B13: ALPHABET INC-CL A | C13: Communication Services | D13: 347.68 | E13: 0.003492366 | F13: 0.0198287 | G13: 429.24686 | H13: =(G13-D13)/D13 | I13: =D13*0.93 | J13: =D13-I13 | K13: =G13-D13 | L13: =IF(J13>0, K13/J13, 0) | M13: =IF(L13>=3.0, "STRONG BUY (3:1+)", IF(L13>=2.0, "QUALIFIED (2:1+)", "MONITOR")) | N13: 64 | O13: 7 | P13: 0 | Q13: =IF((N13+O13+P13)>0, N13/(N13+O13+P13), 0) | R13: 49.548547 | S13: 33.616019 | T13: 4233757895000 | U13: 18348087 | V13: 2026-10-28
A14: WMT | B14: WALMART INC | C14: Consumer Staples | D14: 107.2 | E14: 0.0202722 | F14: 0.003745318 | G14: 128.28889 | H14: =(G14-D14)/D14 | I14: =D14*0.93 | J14: =D14-I14 | K14: =G14-D14 | L14: =IF(J14>0, K14/J14, 0) | M14: =IF(L14>=3.0, "STRONG BUY (3:1+)", IF(L14>=2.0, "QUALIFIED (2:1+)", "MONITOR")) | N14: 46 | O14: 5 | P14: 1 | Q14: =IF((N14+O14+P14)>0, N14/(N14+O14+P14), 0) | R14: 23.441714 | S14: 37.90012 | T14: 8.504976e+11 | U14: 21668064 | V14: 2026-11-19
A15: MA | B15: MASTERCARD INC - A | C15: Financials | D15: 566.58 | E15: 0.003524682 | F15: 0.005323113 | G15: 670.56097 | H15: =(G15-D15)/D15 | I15: =D15*0.93 | J15: =D15-I15 | K15: =G15-D15 | L15: =IF(J15>0, K15/J15, 0) | M15: =IF(L15>=3.0, "STRONG BUY (3:1+)", IF(L15>=2.0, "QUALIFIED (2:1+)", "MONITOR")) | N15: 46 | O15: 3 | P15: 0 | Q15: =IF((N15+O15+P15)>0, N15/(N15+O15+P15), 0) | R15: 241.48841 | S15: 29.884501 | T15: 4.964384e+11 | U15: 2286490 | V15: 2026-10-30
A16: CAT | B16: CATERPILLAR INC | C16: Industrials | D16: 863.44 | E16: 0.01803947 | F16: 0.04451757 | G16: 1007.1632 | H16: =(G16-D16)/D16 | I16: =D16*0.93 | J16: =D16-I16 | K16: =G16-D16 | L16: =IF(J16>0, K16/J16, 0) | M16: =IF(L16>=3.0, "STRONG BUY (3:1+)", IF(L16>=2.0, "QUALIFIED (2:1+)", "MONITOR")) | N16: 17 | O16: 11 | P16: 0 | Q16: =IF((N16+O16+P16)>0, N16/(N16+O16+P16), 0) | R16: 56.989699 | S16: 36.719315 | T16: 3.9690169e+11 | U16: 1961592 | V16: 2026-10-29
... A29: AMD | B29: ADVANCED MICRO DEVICES | C29: Information Technology | D29: 649.42 | E29: 0.02796992 | F29: 0.06888095 | G29: 648.96979 | H29: =(G29-D29)/D29 | I29: =D29*0.93 | J29: =D29-I29 | K29: =G29-D29 | L29: =IF(J29>0, K29/J29, 0) | M29: =IF(L29>=3.0, "STRONG BUY (3:1+)", IF(L29>=2.0, "QUALIFIED (2:1+)", "MONITOR")) | N29: 56 | O29: 12 | P29: 0 | Q29: =IF((N29+O29+P29)>0, N29/(N29+O29+P29), 0) | R29: 10.141147 | S29: 180.3158 | T29: 1.0601619e+12 | U29: 24153966 | V29: 2026-11-04

Sheet 20pct Portfolio Sizer
A1: DALLAS COLLEGE 20% POSITION SIZING & COMPOUNDING CALCULATOR
A2: Enforces the mandatory 20% portfolio entry limit. Change the Total Portfolio Cash below to recalculate all sizing clips.
A4: TOTAL PORTFOLIO CASH ($): | B4: 1000000
A5: MAX 20% ALLOCATION CEILING: | B5: =B4*0.20
A6: PORTFOLIO RISK BUDGET (2% MAX): | B6: =B4*0.02
A8: SLOT # | B8: TICKER | C8: ENTRY PRICE | D8: TARGET PRICE | E8: STOP LOSS PRICE | F8: ALLOCATED $ (20% MAX) | G8: SHARES TO BUY | H8: ACTUAL POSITION $ | I8: PORTFOLIO WEIGHT % | J8: MAX RISK $ (7% STOP) | K8: TARGET PROFIT $ | L8: REBALANCED CASH BALANCE
A9: Position 1 | B9: NVDA | C9: ='Remote Live Screener'!D5 | D9: ='Remote Live Screener'!G5 | E9: ='Remote Live Screener'!I5 | F9: =$B$5 | G9: =INT(F9/C9) | H9: =G9*C9 | I9: =H9/$B$4 | J9: =G9*(C9-E9) | K9: =G9*(D9-C9) | L9: =$B$4+K9
A10: Position 2 | B10: AVGO | C10: ='Remote Live Screener'!D6 | D10: ='Remote Live Screener'!G6 | E10: ='Remote Live Screener'!I6 | F10: =$B$5 | G10: =INT(F10/C10) | H10: =G10*C10 | I10: =H10/$B$4 | J10: =G10*(C10-E10) | K10: =G10*(D10-C10) | L10: =$B$4+K10
A11: Position 3 | B11: LLY | C11: ='Remote Live Screener'!D7 | D11: ='Remote Live Screener'!G7 | E11: ='Remote Live Screener'!I7 | F11: =$B$5 | G11: =INT(F11/C11) | H11: =G11*C11 | I11: =H11/$B$4 | J11: =G11*(C11-E11) | K11: =G11*(D11-C11) | L11: =$B$4+K11
A12: Position 4 | B12: CAT | C12: ='Remote Live Screener'!D8 | D12: ='Remote Live Screener'!G8 | E12: ='Remote Live Screener'!I8 | F12: =$B$5 | G12: =INT(F12/C12) | H12: =G12*C12 | I12: =H12/$B$4 | J12: =G12*(C12-E12) | K12: =G12*(D12-C12) | L12: =$B$4+K12
A13: Position 5 | B13: AMZN | C13: ='Remote Live Screener'!D9 | D13: ='Remote Live Screener'!G9 | E13: ='Remote Live Screener'!I9 | F13: =$B$5 | G13: =INT(F13/C13) | H13: =G13*C13 | I13: =H13/$B$4 | J13: =G13*(C13-E13) | K13: =G13*(D13-C13) | L13: =$B$4+K13
A14: TOTAL ALLOCATED | H14: =SUM(H9:H13) | I14: =SUM(I9:I13) | J14: =SUM(J9:J13) | K14: =SUM(K9:K13)

Sheet Earnings Catalyst Calendar
A1: UPCOMING EARNINGS & CATALYST PIPELINE
A2: Tracks stocks approaching earnings catalyst windows for rapid pre-announcement momentum and post-catalyst compounding.
A4: SYMBOL | B4: COMPANY NAME | C4: SECTOR | D4: LAST PRICE | E4: EXPECTED EARNINGS DATE | F4: CONSENSUS TARGET | G4: UPSIDE % | H4: WALL ST BUY % | I4: PLAYBOOK CATALYST STATUS
A5: JPM | B5: JPMORGAN CHASE & CO | C5: Financials | D5: 331.28 | E5: 2026-10-13 | F5: 371.91577 | G5: =(F5-D5)/D5 | H5: 0.51515152 | I5: =IF(G5>=0.25, "HIGH CONVICTION CATALYST", IF(G5>=0.10, "MONITORING CATALYST", "SECONDARY"))
A6: UNH | B6: UNITEDHEALTH GROUP INC | C6: Health Care | D6: 376.32 | E6: 2026-10-13 | F6: 481.11111 | G6: =(F6-D6)/D6 | H6: 0.83333333 | I6: =IF(G6>=0.25, "HIGH CONVICTION CATALYST", IF(G6>=0.10, "MONITORING CATALYST", "SECONDARY"))
A7: GS | B7: GOLDMAN SACHS GROUP INC | C7: Financials | D7: 897.18 | E7: 2026-10-13 | F7: 1123.7727 | G7: =(F7-D7)/D7 | H7: 0.39285714 | I7: =IF(G7>=0.25, "HIGH CONVICTION CATALYST", IF(G7>=0.10, "MONITORING CATALYST", "SECONDARY"))
A8: JNJ | B8: JOHNSON & JOHNSON | C8: Health Care | D8: 254.78 | E8: 2026-10-13 | F8: 284.04001 | G8: =(F8-D8)/D8 | H8: 0.74074074 | I8: =IF(G8>=0.25, "HIGH CONVICTION CATALYST", IF(G8>=0.10, "MONITORING CATALYST", "SECONDARY"))
A9: RTX | B9: RTX CORP | C9: Industrials | D9: 183.29 | E9: 2026-10-20 | F9: 230.56522 | G9: =(F9-D9)/D9 | H9: 0.7037037 | I9: =IF(G9>=0.25, "HIGH CONVICTION CATALYST", IF(G9>=0.10, "MONITORING CATALYST", "SECONDARY"))
A10: GE | B10: GENERAL ELECTRIC | C10: Industrials | D10: 309.39 | E10: 2026-10-20 | F10: 393 | G10: =(F10-D10)/D10 | H10: 0.80769231 | I10: =IF(G10>=0.25, "HIGH CONVICTION CATALYST", IF(G10>=0.10, "MONITORING CATALYST", "SECONDARY"))
A11: TSLA | B11: TESLA INC | C11: Consumer Discretionary | D11: 380.68 | E11: 2026-10-21 | F11: 393.65976 | G11: =(F11-D11)/D11 | H11: 0.47540984 | I11: =IF(G11>=0.25, "HIGH CONVICTION CATALYST", IF(G11>=0.10, "MONITORING CATALYST", "SECONDARY"))
A12: LMT | B12: LOCKHEED MARTIN CORP | C12: Industrials | D12: 510.12 | E12: 2026-10-22 | F12: 638.82611 | G12: =(F12-D12)/D12 | H12: 0.48148148 | I12: =IF(G12>=0.25, "HIGH CONVICTION CATALYST", IF(G12>=0.10, "MONITORING CATALYST", "SECONDARY"))
A13: V | B13: VISA INC-CLASS A SHARES | C13: Financials | D13: 370.64 | E13: 2026-10-28 | F13: 424.39026 | G13: =(F13-D13)/D13 | H13: 0.9375 | I13: =IF(G13>=0.25, "HIGH CONVICTION CATALYST", IF(G13>=0.10, "MONITORING CATALYST", "SECONDARY"))
A14: GOOGL | B14: ALPHABET INC-CL A | C14: Communication Services | D14: 347.68 | E14: 2026-10-28 | F14: 429.24686 | G14: =(F14-D14)/D14 | H14: 0.90140845 | I14: =IF(G14>=0.25, "HIGH CONVICTION CATALYST", IF(G14>=0.10, "MONITORING CATALYST", "SECONDARY"))
A15: CAT | B15: CATERPILLAR INC | C15: Industrials | D15: 863.44 | E15: 2026-10-29 | F15: 1007.1632 | G15: =(F15-D15)/D15 | H15: 0.60714286 | I15: =IF(G15>=0.25, "HIGH CONVICTION CATALYST", IF(G15>=0.10, "MONITORING CATALYST", "SECONDARY"))
A16: MSFT | B16: MICROSOFT CORP | C16: Information Technology | D16: 529.3 | E16: 2026-10-29 | F16: 580.32928 | G16: =(F16-D16)/D16 | H16: 0.97222222 | I16: =IF(G16>=0.25, "HIGH CONVICTION CATALYST", IF(G16>=0.10, "MONITORING CATALYST", "SECONDARY"))
... A29: AVGO | B29: BROADCOM INC | C29: Information Technology | D29: 375.81 | E29: 2026-12-11 | F29: 529.70209 | G29: =(F29-D29)/D29 | H29: 0.93548387 | I29: =IF(G29>=0.25, "HIGH CONVICTION CATALYST", IF(G29>=0.10, "MONITORING CATALYST", "SECONDARY"))
